lbcgo/00ToDo
lbcgo/LBCgo.py.bak
lbcgo/__init__.py
lbcgo/conf/default.conv
lbcgo/conf/default.nnw
lbcgo/conf/scamp.lbc.conf
lbcgo/conf/sextractor.lbc.conf
lbcgo/conf/sextractor.lbcoutput.param
lbcgo/conf/swarp.lbc.conf
lbcgo/examples/modsProc.py
lbcgo/examples/pyhrs.py
lbcgo/examples/pypit.py
lbcgo/examples/reduceccd_example.py
lbcgo/examples/wht_basicredux.py
lbcgo/lbcproc.py
lbcgo/lbcregister.py
lbcgo/whatidid.astrom.py
lbcgo-0.1.6.dist-info/LICENSE
lbcgo-0.1.6.dist-info/METADATA
lbcgo-0.1.6.dist-info/WHEEL
lbcgo-0.1.6.dist-info/RECORD
