Metadata-Version: 2.3
Name: LBCgo
Version: 0.1.6
Summary: Data reduction for the LBT's Large Binocular Camera
License: MIT
Author: Chris Howk
Author-email: jhowk@nd.edu
Requires-Python: >=3.8
Classifier: License :: OSI Approved :: MIT License
Classifier: Programming Language :: Python :: 3
Classifier: Programming Language :: Python :: 3.8
Classifier: Programming Language :: Python :: 3.9
Classifier: Programming Language :: Python :: 3.10
Classifier: Programming Language :: Python :: 3.11
Classifier: Programming Language :: Python :: 3.12
Classifier: Programming Language :: Python :: 3.13
Requires-Dist: astropy (>=5.3.3,<6.0.0)
Requires-Dist: ccdproc (>=2.2.0,<3.0.0)
Requires-Dist: numpy (>=1.21,<2.0)
Project-URL: Homepage, https://github.com/jchowk/LBCgo
